interfaced/__init__.py
interfaced/core/__init__.py
interfaced/core/exceptions.py
interfaced/core/types.py
interfaced/core/validation.py
interfaced/decorators/__init__.py
interfaced/decorators/implementation.py
interfaced/decorators/interface.py
interfaced/metadata/__init__.py
interfaced/metadata/cache.py
interfaced/metadata/interface_meta.py
interfaced/metadata/signature.py
interfaced/registry/__init__.py
interfaced/registry/implementation_registry.py
interfaced/system/__init__.py
interfaced/system/interface_system.py
interfaced-0.1.0.dist-info/LICENSE
interfaced-0.1.0.dist-info/METADATA
interfaced-0.1.0.dist-info/WHEEL
interfaced-0.1.0.dist-info/RECORD
