Metadata-Version: 2.3
Name: interfaced
Version: 0.1.0
Summary: Python interface system
Author: anybody
Requires-Python: >=3.12,<4.0
Classifier: Programming Language :: Python :: 3
Classifier: Programming Language :: Python :: 3.12
Classifier: Programming Language :: Python :: 3.13
